{
	"configurations" : 
	[
		{
			"directories" : 
			[
				{
					"build" : ".",
					"childIndexes" : 
					[
						1
					],
					"hasInstallRule" : true,
					"jsonFile" : "directory-.-Debug-d0094a50bb2071803777.json",
					"minimumCMakeVersion" : 
					{
						"string" : "3.27"
					},
					"projectIndex" : 0,
					"source" : ".",
					"targetIndexes" : 
					[
						1
					]
				},
				{
					"build" : "enet-master",
					"hasInstallRule" : true,
					"jsonFile" : "directory-enet-master-Debug-c9b12ecd904069f972c1.json",
					"minimumCMakeVersion" : 
					{
						"string" : "2.8.12"
					},
					"parentIndex" : 0,
					"projectIndex" : 1,
					"source" : "enet-master",
					"targetIndexes" : 
					[
						0,
						2
					]
				}
			],
			"name" : "Debug",
			"projects" : 
			[
				{
					"childIndexes" : 
					[
						1
					],
					"directoryIndexes" : 
					[
						0
					],
					"name" : "FinalProject",
					"targetIndexes" : 
					[
						1
					]
				},
				{
					"directoryIndexes" : 
					[
						1
					],
					"name" : "enet",
					"parentIndex" : 0,
					"targetIndexes" : 
					[
						0,
						2
					]
				}
			],
			"targets" : 
			[
				{
					"directoryIndex" : 1,
					"id" : "EnetTest::@0c6eceeb80d584af62a4",
					"jsonFile" : "target-EnetTest-Debug-7af426b189d5f4b4e688.json",
					"name" : "EnetTest",
					"projectIndex" : 1
				},
				{
					"directoryIndex" : 0,
					"id" : "FinalProject::@6890427a1f51a3e7e1df",
					"jsonFile" : "target-FinalProject-Debug-b838dd8e7edec424e48c.json",
					"name" : "FinalProject",
					"projectIndex" : 0
				},
				{
					"directoryIndex" : 1,
					"id" : "enet::@0c6eceeb80d584af62a4",
					"jsonFile" : "target-enet-Debug-155db3d861b542a3cfd0.json",
					"name" : "enet",
					"projectIndex" : 1
				}
			]
		}
	],
	"kind" : "codemodel",
	"paths" : 
	{
		"build" : "C:/Users/annys/Downloads/FinalProject/build",
		"source" : "C:/Users/annys/Downloads/FinalProject/MyGame"
	},
	"version" : 
	{
		"major" : 2,
		"minor" : 7
	}
}
